gk_calculator/__init__.py
gk_calculator/calculator.py
gk_calculator-1.0.0.dist-info/LICENSE.txt
gk_calculator-1.0.0.dist-info/METADATA
gk_calculator-1.0.0.dist-info/WHEEL
gk_calculator-1.0.0.dist-info/top_level.txt
gk_calculator-1.0.0.dist-info/RECORD
