Metadata-Version: 2.1
Name: gk-calculator
Version: 1.0.0
Summary: A advanced calculator program
Home-page: https://github.com/gkibria121/calculator
Author: Ahmed Kibria
Author-email: gkibria121@email.com
Keywords: python,calculator,python calculator,gk calculator,advanced calculator
Classifier: Programming Language :: Python :: 3
Classifier: License :: OSI Approved :: MIT License
Classifier: Operating System :: OS Independent
Requires-Python: >=3.6
License-File: LICENSE.txt
Requires-Dist: regex
